Metadata-Version: 1.0
Name: linkbot-usbjig-programmer
Version: 0.1.1
Summary: Tool for flashing Linkbot main-boards with a bootloader onthe main programming jig.
Home-page: UNKNOWN
Author: David Ko
Author-email: david@barobo.com
License: UNKNOWN
Platform: UNKNOWN
